{
  "type_description_msg": {
    "type_description": {
      "type_name": "study_interface/msg/Line",
      "fields": [
        {
          "name": "low_x",
          "type": {
            "type_id": 155,
            "capacity": 0,
            "string_capacity": 0,
            "nested_type_name": ""
          },
          "default_value": ""
        },
        {
          "name": "high_x",
          "type": {
            "type_id": 155,
            "capacity": 0,
            "string_capacity": 0,
            "nested_type_name": ""
          },
          "default_value": ""
        },
        {
          "name": "low_y",
          "type": {
            "type_id": 155,
            "capacity": 0,
            "string_capacity": 0,
            "nested_type_name": ""
          },
          "default_value": ""
        },
        {
          "name": "high_y",
          "type": {
            "type_id": 155,
            "capacity": 0,
            "string_capacity": 0,
            "nested_type_name": ""
          },
          "default_value": ""
        },
        {
          "name": "a",
          "type": {
            "type_id": 155,
            "capacity": 0,
            "string_capacity": 0,
            "nested_type_name": ""
          },
          "default_value": ""
        },
        {
          "name": "b",
          "type": {
            "type_id": 155,
            "capacity": 0,
            "string_capacity": 0,
            "nested_type_name": ""
          },
          "default_value": ""
        },
        {
          "name": "c",
          "type": {
            "type_id": 155,
            "capacity": 0,
            "string_capacity": 0,
            "nested_type_name": ""
          },
          "default_value": ""
        },
        {
          "name": "distance",
          "type": {
            "type_id": 155,
            "capacity": 0,
            "string_capacity": 0,
            "nested_type_name": ""
          },
          "default_value": ""
        },
        {
          "name": "theta",
          "type": {
            "type_id": 155,
            "capacity": 0,
            "string_capacity": 0,
            "nested_type_name": ""
          },
          "default_value": ""
        }
      ]
    },
    "referenced_type_descriptions": []
  },
  "type_hashes": [
    {
      "type_name": "study_interface/msg/Line",
      "hash_string": "RIHS01_db13c61a142bed6dce5c9b285208fbd4c84c75451cc9b1175ede15f0825f4687"
    }
  ]
}